jsonpath2/__init__.py
jsonpath2/expression.py
jsonpath2/node.py
jsonpath2/path.py
jsonpath2/subscript.py
jsonpath2/tojsonpath.py
jsonpath2/expressions/__init__.py
jsonpath2/expressions/operator.py
jsonpath2/expressions/some.py
jsonpath2/nodes/__init__.py
jsonpath2/nodes/current.py
jsonpath2/nodes/recursivedescent.py
jsonpath2/nodes/root.py
jsonpath2/nodes/subscript.py
jsonpath2/nodes/terminal.py
jsonpath2/parser/JSONPathLexer.py
jsonpath2/parser/JSONPathListener.py
jsonpath2/parser/JSONPathParser.py
jsonpath2/parser/__init__.py
jsonpath2/subscripts/__init__.py
jsonpath2/subscripts/arrayindex.py
jsonpath2/subscripts/arrayslice.py
jsonpath2/subscripts/callable.py
jsonpath2/subscripts/filter.py
jsonpath2/subscripts/node.py
jsonpath2/subscripts/objectindex.py
jsonpath2/subscripts/wildcard.py
jsonpath2-0.4.5.dist-info/LICENSE
jsonpath2-0.4.5.dist-info/METADATA
jsonpath2-0.4.5.dist-info/WHEEL
jsonpath2-0.4.5.dist-info/top_level.txt
jsonpath2-0.4.5.dist-info/RECORD
