Metadata-Version: 2.1
Name: jsonpath2
Version: 0.4.5
Summary: JSONPath implementation for Python
Home-page: https://github.com/pacifica/python-jsonpath2/
Author: Mark Borkum
Author-email: mark.borkum@pnnl.gov
License: LGPLv3
Platform: UNKNOWN
License-File: LICENSE
Requires-Dist: antlr4-python3-runtime (==4.10)
